LICENSE
MANIFEST.in
README.md
install.json
package.json
pyproject.toml
setup.cfg
setup.py
tsconfig.json
tslint.json
yarn.lock
jupyter-config/sn_jupyterlab_github.json
sn_jupyterlab_github/__init__.py
sn_jupyterlab_github.egg-info/PKG-INFO
sn_jupyterlab_github.egg-info/SOURCES.txt
sn_jupyterlab_github.egg-info/dependency_links.txt
sn_jupyterlab_github.egg-info/not-zip-safe
sn_jupyterlab_github.egg-info/requires.txt
sn_jupyterlab_github.egg-info/top_level.txt
sn_jupyterlab_github/labextension/package.json
sn_jupyterlab_github/labextension/schemas/sn-jupyterlab-github/drive.json
sn_jupyterlab_github/labextension/schemas/sn-jupyterlab-github/package.json.orig
sn_jupyterlab_github/labextension/static/060d51417beb0f47daa10a4dcb2e147d.png
sn_jupyterlab_github/labextension/static/523.0db4c345b1637dc4184a.js
sn_jupyterlab_github/labextension/static/534.84f5dd78e61a4acfc961.js
sn_jupyterlab_github/labextension/static/d8c6d6c90bdccf76d860cc3f6dddb39c.png
sn_jupyterlab_github/labextension/static/remoteEntry.d21ced56b4194bdef55e.js
sn_jupyterlab_github/labextension/static/style.js
src/cclabs-authentication.ts
src/cclabs-context-menu.ts
src/cclabs-gist-sharing.ts
src/index.ts
style/base.css
style/binder.svg
style/cclabs.css
style/index.css
style/index.js
style/octocat-dark.svg
style/octocat-light.svg
style/octocat.png
style/octocat_error.png
style/sign-in.svg