Metadata-Version: 2.1
Name: sn-jupyterlab-github
Version: 3.0.3
Summary: JupyterLab viewer for GitHub repositories
Home-page: https://github.ibm.com/skills-network-labs/jupyterlab-github
Author: Ian Rose (and modified by James Reeve)
License: BSD-3-Clause
Keywords: Jupyter,JupyterLab,JupyterLab3
Platform: Linux
Platform: Mac OS X
Platform: Windows
Classifier: License :: OSI Approved :: BSD License
Classifier: Programming Language :: Python
Classifier: Programming Language :: Python :: 3
Classifier: Programming Language :: Python :: 3.6
Classifier: Programming Language :: Python :: 3.7
Classifier: Programming Language :: Python :: 3.8
Classifier: Programming Language :: Python :: 3.9
Classifier: Framework :: Jupyter
Requires-Python: >=3.6
